monaco_assets/__init__.py
monaco_assets-0.5.1.dist-info/WHEEL
monaco_assets-0.5.1.dist-info/METADATA
monaco_assets-0.5.1.dist-info/RECORD
