Metadata-Version: 2.4
Name: monaco-assets
Version: 0.5.1
Summary: Automatically download Monaco editor assets.
Keywords: monaco,assets
Requires-Python: >=3.10
License-Expression: MIT
Classifier: Development Status :: 4 - Beta
Classifier: Intended Audience :: Developers
Classifier: Programming Language :: Python :: 3
Classifier: Programming Language :: Python :: 3.10
Classifier: Programming Language :: Python :: 3.11
Classifier: Programming Language :: Python :: 3.12
Classifier: Programming Language :: Python :: 3.13
Classifier: Topic :: Software Development :: Libraries
Requires-Dist: certifi
Requires-Dist: platformdirs
Requires-Dist: fastapi
Requires-Dist: uvicorn
Project-URL: homepage, https://github.com/andythomas/monaco-assets
